Metadata-Version: 2.1
Name: CompleteBin
Version: 1.1.0.2
Summary: The binner to cluster contigs.
Home-page: UNKNOWN
Author: Bohao Zou
Author-email: csbhzou@comp.hkbu.edu.hk
License: UNKNOWN
Platform: UNKNOWN
Requires-Python: >=3.9
License-File: LICENSE
Requires-Dist: psutil (>=6.1.0)
Requires-Dist: contourpy (>=1.3.0)
Requires-Dist: cycler (>=0.12.1)
Requires-Dist: dendropy (>=5.0.1)
Requires-Dist: filelock (>=3.13.1)
Requires-Dist: flspp-modified (>=1.3)
Requires-Dist: fonttools (>=4.55.3)
Requires-Dist: fsspec (>=2024.2.0)
Requires-Dist: hnswlib (>=0.8.0)
Requires-Dist: igraph (>=0.11.8)
Requires-Dist: checkm2-modified (==1.0.2)
Requires-Dist: importlib-resources (>=6.4.5)
Requires-Dist: jinja2 (>=3.1.3)
Requires-Dist: kiwisolver (>=1.4.7)
Requires-Dist: checkm-genome (==1.2.3)
Requires-Dist: leidenalg (>=0.10.2)
Requires-Dist: matplotlib (>=3.9.4)
Requires-Dist: mpmath (>=1.3.0)
Requires-Dist: networkx (>=3.2.1)
Requires-Dist: pillow (>=10.2.0)
Requires-Dist: pyparsing (>=3.2.0)
Requires-Dist: pysam (>=0.22.1)
Requires-Dist: sympy (>=1.13.1)
Requires-Dist: texttable (>=1.7.0)
